{
  "$schema": "https://raw.githubusercontent.com/googleapis/release-please/main/schemas/config.json",
  "bootstrap-sha": "60ba52f45b717aef0ef985f649938fb0b5ab7f6b",
  "packages": {
    ".": {
      "release-type": "node",
      "changelog-path": "CHANGELOG.md"
    }
  },
  "pull-request-title-pattern": "chore: release ${version}",
  "changelog-sections": [
    { "type": "feat", "section": "Features" },
    { "type": "fix", "section": "Bug Fixes" },
    { "type": "perf", "section": "Performance Improvements" },
    { "type": "revert", "section": "Reverts" },
    { "type": "docs", "section": "Documentation" },
    { "type": "ci", "section": "CI" },
    { "type": "chore", "section": "Miscellaneous", "hidden": true }
  ]
}
